MANIFEST.in
README.md
requirements-dev.txt
requirements.txt
setup.py
django_master.egg-info/PKG-INFO
django_master.egg-info/SOURCES.txt
django_master.egg-info/dependency_links.txt
django_master.egg-info/not-zip-safe
django_master.egg-info/requires.txt
django_master.egg-info/top_level.txt
djangomaster/__init__.py
djangomaster/conf.py
djangomaster/core.py
djangomaster/factories.py
djangomaster/models.py
djangomaster/sites.py
djangomaster/utils.py
djangomaster/version.txt
djangomaster/views.py
djangomaster/widgets.py
djangomaster/master/__init__.py
djangomaster/master/home.py
djangomaster/master/migrations.py
djangomaster/master/models.py
djangomaster/master/routes.py
djangomaster/master/signals.py
djangomaster/master/templatetags.py
djangomaster/static/.DS_Store
djangomaster/static/djangomaster/.DS_Store
djangomaster/static/djangomaster/sbadmin/LICENSE
djangomaster/static/djangomaster/sbadmin/README.md
djangomaster/static/djangomaster/sbadmin/css/.DS_Store
djangomaster/static/djangomaster/sbadmin/css/bootstrap.min.css
djangomaster/static/djangomaster/sbadmin/css/sb-admin-2.css
djangomaster/static/djangomaster/sbadmin/css/plugins/.DS_Store
djangomaster/static/djangomaster/sbadmin/css/plugins/dataTables.bootstrap.css
djangomaster/static/djangomaster/sbadmin/css/plugins/morris.css
djangomaster/static/djangomaster/sbadmin/css/plugins/social-buttons.css
djangomaster/static/djangomaster/sbadmin/css/plugins/timeline.css
djangomaster/static/djangomaster/sbadmin/css/plugins/metisMenu/metisMenu.css
djangomaster/static/djangomaster/sbadmin/css/plugins/metisMenu/metisMenu.min.css
djangomaster/static/djangomaster/sbadmin/font-awesome/css/font-awesome.css
djangomaster/static/djangomaster/sbadmin/font-awesome/css/font-awesome.min.css
djangomaster/static/djangomaster/sbadmin/font-awesome/fonts/FontAwesome.otf
djangomaster/static/djangomaster/sbadmin/font-awesome/fonts/fontawesome-webfont.eot
djangomaster/static/djangomaster/sbadmin/font-awesome/fonts/fontawesome-webfont.svg
djangomaster/static/djangomaster/sbadmin/font-awesome/fonts/fontawesome-webfont.ttf
djangomaster/static/djangomaster/sbadmin/font-awesome/fonts/fontawesome-webfont.woff
