Metadata-Version: 1.0
Name: django-master
Version: 0.2.7
Summary: django master dashboard
Home-page: http://github.com/django-master/django-master
Author: Andre Farzat
Author-email: andrefarzat@gmail.com
License: LICENSE
Platform: UNKNOWN
